svg2eagle/__init__.py
svg2eagle/svg2eagle.py
svg2eagle-1.1.6.dist-info/LICENSE
svg2eagle-1.1.6.dist-info/METADATA
svg2eagle-1.1.6.dist-info/WHEEL
svg2eagle-1.1.6.dist-info/entry_points.txt
svg2eagle-1.1.6.dist-info/top_level.txt
svg2eagle-1.1.6.dist-info/RECORD
