Metadata-Version: 2.1
Name: svg2eagle
Version: 1.1.6
Summary: python package for converting svg to eagle polygons
Home-page: https://github.com/menga-team/svg2eagle
Author: Nakano Miku
Author-email: nakanomiku@menga.org
Project-URL: Bug Tracker, https://github.com/menga-team/svg2eagle/issues
Classifier: Programming Language :: Python :: 3
Classifier: License :: OSI Approved :: MIT License
Classifier: Operating System :: OS Independent
Requires-Python: >=3.6
License-File: LICENSE
Requires-Dist: tqdm
Requires-Dist: svg.path
Requires-Dist: shapely
Requires-Dist: matplotlib
Requires-Dist: anytree
